Ficamacos/__init__.py
Ficamacos/method.py
Ficamacos/model.py
Ficamacos-0.1.0.dist-info/LICENSE.md
Ficamacos-0.1.0.dist-info/METADATA
Ficamacos-0.1.0.dist-info/WHEEL
Ficamacos-0.1.0.dist-info/top_level.txt
Ficamacos-0.1.0.dist-info/RECORD
